myouji_kenchi/__init__.py
myouji_kenchi/kenchi.py
myouji_kenchi/symbol_table.py
myouji_kenchi/transducer.py
myouji_kenchi/data/lexical_data_fst.txt
myouji_kenchi-1.0.1.dist-info/LICENSE.txt
myouji_kenchi-1.0.1.dist-info/METADATA
myouji_kenchi-1.0.1.dist-info/RECORD
myouji_kenchi-1.0.1.dist-info/WHEEL
myouji_kenchi-1.0.1.dist-info/top_level.txt
