Metadata-Version: 2.1
Name: myouji-kenchi
Version: 1.0.1
Summary: Determine if romanized Japanese names are family names
Home-page: https://github.com/scouty-inc/myouji-kenchi
Author: Derick Anderson
Author-email: anderson.derick.w@gmail.com
License: UNKNOWN
Platform: UNKNOWN
Classifier: Programming Language :: Python :: 3
Classifier: License :: OSI Approved :: MIT License
Classifier: Operating System :: OS Independent
Classifier: Natural Language :: Japanese
Classifier: Topic :: Text Processing :: Linguistic
Requires-Dist: numpy
Requires-Dist: openfst (>=1.6.6<1.6.7)
Requires-Dist: regex
